PyEzEmail/__init__.py
PyEzEmail-0.0.4.dist-info/LICENSE
PyEzEmail-0.0.4.dist-info/METADATA
PyEzEmail-0.0.4.dist-info/WHEEL
PyEzEmail-0.0.4.dist-info/top_level.txt
PyEzEmail-0.0.4.dist-info/RECORD
