Metadata-Version: 2.1
Name: PyEzEmail
Version: 0.0.4
Summary: Libreria para facilitar el envio de mails
Home-page: https://github.com/shinraxor
Author: Pedro Lamarca
Author-email: pedro.lamarca.1997@gmail.com
License: MIT
Platform: UNKNOWN
License-File: LICENSE
